SolrAPI.py
setup.py
SolrAPI.egg-info/PKG-INFO
SolrAPI.egg-info/SOURCES.txt
SolrAPI.egg-info/dependency_links.txt
SolrAPI.egg-info/requires.txt
SolrAPI.egg-info/top_level.txt