Metadata-Version: 1.1
Name: SolrAPI
Version: 1.2.0
Summary: Python implementation of the main operation in the Solr API Rest
Home-page: https://github.com/picleslivre/solrapi
Author: Jamil Atta
Author-email: atta.jamil@gmail.com
License: BSD
Keywords: solr api lucene rest
Platform: UNKNOWN
Classifier: Topic :: System
Classifier: Topic :: Utilities
Classifier: Programming Language :: Python
Classifier: Operating System :: POSIX :: Linux
Classifier: Development Status :: 1 - Planning
Classifier: Intended Audience :: Customer Service
Classifier: License :: OSI Approved :: BSD License
Classifier: Natural Language :: Portuguese (Brazilian)
Classifier: Topic :: Internet :: WWW/HTTP :: Indexing/Search
Classifier: Topic :: Software Development :: Libraries :: Python Modules
